jaxdlm/__init__.py
jaxdlm/base.py
jaxdlm-0.0.2.dist-info/METADATA
jaxdlm-0.0.2.dist-info/WHEEL
jaxdlm-0.0.2.dist-info/licenses/LICENSE
jaxdlm-0.0.2.dist-info/RECORD
