Metadata-Version: 2.1
Name: jaxdlm
Version: 0.0.2
Summary: A Jax based python package for dynamic linear models
Project-URL: GitHub, https://github.com/michaelellis003/JaxDLM
Author-email: Michael Ellis <michael@mlellis.com>
License-File: LICENSE
Keywords: dynamic linear models,jax,state space models,time series
Classifier: License :: OSI Approved :: MIT License
Classifier: Operating System :: OS Independent
Classifier: Programming Language :: Python :: 3
Requires-Python: >=3.8
